PyFiTransfer/CLI_main.py
PyFiTransfer/__init__.py
PyFiTransfer/main.py
PyFiTransfer/appevents/CLI_loop.py
PyFiTransfer/appevents/GUI_loop.py
PyFiTransfer/appevents/__init__.py
PyFiTransfer/appevents/events.py
PyFiTransfer/appgui/__init__.py
PyFiTransfer/appgui/gui.py
PyFiTransfer/applogger/__init__.py
PyFiTransfer/applogger/logger.py
PyFiTransfer/logs/.gitkeep
PyFiTransfer-0.4.1.dist-info/LICENSE
PyFiTransfer-0.4.1.dist-info/METADATA
PyFiTransfer-0.4.1.dist-info/WHEEL
PyFiTransfer-0.4.1.dist-info/entry_points.txt
PyFiTransfer-0.4.1.dist-info/top_level.txt
PyFiTransfer-0.4.1.dist-info/RECORD
