Metadata-Version: 2.1
Name: PyFiTransfer
Version: 0.4.1
Summary: Transfer files with specified extension-type from a starting directory to desired target directory.
Home-page: https://github.com/schlopp96/PyFiTransfer
Author: schlopp96
Author-email: schloppdaddy@gmail.com
License: UNKNOWN
Keywords: file,transfer,script,files,directory,directories,extension,extensions,rename-files,rename-file,move-file,move-files
Platform: UNKNOWN
Classifier: Development Status :: 3 - Alpha
Classifier: Intended Audience :: Developers
Classifier: Intended Audience :: End Users/Desktop
Classifier: License :: OSI Approved :: GNU General Public License v3 (GPLv3)
Classifier: Natural Language :: English
Classifier: Operating System :: Microsoft :: Windows
Classifier: Programming Language :: Python :: 3
Classifier: Programming Language :: Python :: 3.9
Classifier: Programming Language :: Python :: 3.10
Classifier: Topic :: Software Development :: Libraries :: Python Modules
Classifier: Topic :: Utilities
License-File: LICENSE
Requires-Dist: PyLoadBar (>=0.1.0)
Requires-Dist: PySimpleGUI (>=4.60.1)
Requires-Dist: setuptools (>=58.1.0)
